MANIFEST.in
README.md
setup.py
python_xbtesting.egg-info/PKG-INFO
python_xbtesting.egg-info/SOURCES.txt
python_xbtesting.egg-info/dependency_links.txt
python_xbtesting.egg-info/requires.txt
python_xbtesting.egg-info/top_level.txt
python_xbtesting.egg-info/zip-safe
xbtesting/__init__.py
xbtesting/xbtesting.py