Metadata-Version: 1.0
Name: python-xbtesting
Version: 0.1.7
Summary: A Python library to talk to the API provided by CrossBrowserTesting.com
Home-page: http://github.com/philippbosch/python-xbtesting/
Author: Philipp Bosch
Author-email: hello@pb.io
License: MIT
Download-URL: http://pypi.python.org/pypi/python-xbtesting/
Keywords: python api crossbrowsertesting
Platform: UNKNOWN
Classifier: Development Status :: 3 - Alpha
Classifier: Environment :: Web Environment
Classifier: Operating System :: OS Independent
Classifier: Programming Language :: Python
Classifier: License :: OSI Approved :: MIT License
